ccrenew/__init__.py
ccrenew/ccr.py
ccrenew/cloud_data.py
ccrenew/data_determination.py
ccrenew/dashboard/__init__.py
ccrenew/dashboard/project.py
ccrenew/dashboard/session.py
ccrenew/dashboard/data_processing/BV_pp_deg.py
ccrenew/dashboard/data_processing/Correct_Meter_data_v08_IS6.py
ccrenew/dashboard/data_processing/Correct_Meter_data_v08_smartercheck.py
ccrenew/dashboard/data_processing/Correct_POI_data_v01.py
ccrenew/dashboard/data_processing/Performance_Guarantees_v01.py
ccrenew/dashboard/data_processing/Plant_Availability_v16_bbsc.py
ccrenew/dashboard/data_processing/Rate_Structure_Python_with_DST_v07.py
ccrenew/dashboard/data_processing/Table_by_Rate_Schedule_v01.py
ccrenew/dashboard/data_processing/__init__.py
ccrenew/dashboard/data_processing/_project_processing.py
ccrenew/dashboard/data_processing/batch_process.py
ccrenew/dashboard/data_processing/battery_deg.py
ccrenew/dashboard/data_processing/snow_loss_functions_v3.py
ccrenew/dashboard/data_processing/solcats_API.py
ccrenew/dashboard/data_processing/weather_adjusted_functions_v03.py
ccrenew/dashboard/plotting/__init__.py
ccrenew/dashboard/plotting/plots.py
ccrenew/dashboard/utils/__init__.py
ccrenew/dashboard/utils/dashboard_utils.py
ccrenew/dashboard/utils/df_tools.py
ccrenew/dashboard/utils/logging_conf.py
ccrenew/dashboard/utils/project_neighbors.py
ccrenew/pvmodel/__init__.py
ccrenew/pvmodel/project_model.py
ccrenew-0.2.1.dist-info/LICENSE
ccrenew-0.2.1.dist-info/METADATA
ccrenew-0.2.1.dist-info/WHEEL
ccrenew-0.2.1.dist-info/top_level.txt
ccrenew-0.2.1.dist-info/RECORD
