Metadata-Version: 2.1
Name: ccrenew
Version: 0.2.1
Summary: Utilities for running Cypress Creek Renewables Performance Engineering workflows
Home-page: https://cypresscreekrenew.sharepoint.com/:u:/s/AM-Performance/EdhVQHbS4n9Jm022irFSFiABmo6gcEW3KTmV0qEkfHW84Q?e=zxokuU
Author: CCR Perf Eng Team
Requires-Python: >=3.8
License-File: LICENSE
